shutdown_computer/__init__.py
shutdown_computer/main.py
shutdown_computer-0.0.2.dist-info/LICENSE
shutdown_computer-0.0.2.dist-info/METADATA
shutdown_computer-0.0.2.dist-info/WHEEL
shutdown_computer-0.0.2.dist-info/top_level.txt
shutdown_computer-0.0.2.dist-info/RECORD
