Metadata-Version: 2.1
Name: shutdown_computer
Version: 0.0.2
Summary: A package shutdown computer
Author-email: Min <minha05112003a@gmail.com>
Project-URL: Homepage, https://github.com/min-awm/shutdown_computer
Project-URL: Issues, https://github.com/min-awm/shutdown_computer/issues
Classifier: Programming Language :: Python :: 3
Classifier: License :: OSI Approved :: MIT License
Classifier: Operating System :: OS Independent
Requires-Python: >=3.8
License-File: LICENSE
